graphql_client/__init__.py
graphql_client/client.py
graphql_client/core.py
graphql_client/utils.py
wf_graphql_client_python-0.0.1.dist-info/LICENSE
wf_graphql_client_python-0.0.1.dist-info/METADATA
wf_graphql_client_python-0.0.1.dist-info/WHEEL
wf_graphql_client_python-0.0.1.dist-info/top_level.txt
wf_graphql_client_python-0.0.1.dist-info/RECORD
